rpibmp/__init__.py
rpibmp/bmp180.py
RpiBmp-0.1.dist-info/METADATA
RpiBmp-0.1.dist-info/WHEEL
RpiBmp-0.1.dist-info/top_level.txt
RpiBmp-0.1.dist-info/RECORD
