Metadata-Version: 2.1
Name: RpiBmp
Version: 0.1
Summary: Simple Rapspberry Pi Python driver for BMP180 and BMP85 modules
Home-page: UNKNOWN
Author: UNKNOWN
Author-email: UNKNOWN
License: UNKNOWN
Platform: UNKNOWN
